calculatorkzv1/.DS_Store
calculatorkzv1/__init__.py
calculatorkzv1/calculatorkzv1.py
calculatorkzv1/.ipynb_checkpoints/__init__-checkpoint.py
calculatorkzv1/.mypy_cache/.gitignore
calculatorkzv1/.mypy_cache/CACHEDIR.TAG
calculatorkzv1/.mypy_cache/3.9/@plugins_snapshot.json
calculatorkzv1/.mypy_cache/3.9/_ast.data.json
calculatorkzv1/.mypy_cache/3.9/_ast.meta.json
calculatorkzv1/.mypy_cache/3.9/_codecs.data.json
calculatorkzv1/.mypy_cache/3.9/_codecs.meta.json
calculatorkzv1/.mypy_cache/3.9/_collections_abc.data.json
calculatorkzv1/.mypy_cache/3.9/_collections_abc.meta.json
calculatorkzv1/.mypy_cache/3.9/_ctypes.data.json
calculatorkzv1/.mypy_cache/3.9/_ctypes.meta.json
calculatorkzv1/.mypy_cache/3.9/abc.data.json
calculatorkzv1/.mypy_cache/3.9/abc.meta.json
calculatorkzv1/.mypy_cache/3.9/array.data.json
calculatorkzv1/.mypy_cache/3.9/array.meta.json
calculatorkzv1/.mypy_cache/3.9/builtins.data.json
calculatorkzv1/.mypy_cache/3.9/builtins.meta.json
calculatorkzv1/.mypy_cache/3.9/codecs.data.json
calculatorkzv1/.mypy_cache/3.9/codecs.meta.json
calculatorkzv1/.mypy_cache/3.9/contextlib.data.json
calculatorkzv1/.mypy_cache/3.9/contextlib.meta.json
calculatorkzv1/.mypy_cache/3.9/enum.data.json
calculatorkzv1/.mypy_cache/3.9/enum.meta.json
calculatorkzv1/.mypy_cache/3.9/genericpath.data.json
calculatorkzv1/.mypy_cache/3.9/genericpath.meta.json
calculatorkzv1/.mypy_cache/3.9/io.data.json
calculatorkzv1/.mypy_cache/3.9/io.meta.json
calculatorkzv1/.mypy_cache/3.9/mmap.data.json
calculatorkzv1/.mypy_cache/3.9/mmap.meta.json
calculatorkzv1/.mypy_cache/3.9/pathlib.data.json
calculatorkzv1/.mypy_cache/3.9/pathlib.meta.json
calculatorkzv1/.mypy_cache/3.9/pickle.data.json
calculatorkzv1/.mypy_cache/3.9/pickle.meta.json
calculatorkzv1/.mypy_cache/3.9/posixpath.data.json
calculatorkzv1/.mypy_cache/3.9/posixpath.meta.json
calculatorkzv1/.mypy_cache/3.9/re.data.json
calculatorkzv1/.mypy_cache/3.9/re.meta.json
calculatorkzv1/.mypy_cache/3.9/sre_compile.data.json
calculatorkzv1-0.1.0.dist-info/LICENSE
calculatorkzv1-0.1.0.dist-info/WHEEL
calculatorkzv1-0.1.0.dist-info/METADATA
calculatorkzv1-0.1.0.dist-info/RECORD
